LICENSE.txt
MANIFEST.in
README.rst
pelican_alias.py
setup.cfg
setup.py
pelican_alias.egg-info/PKG-INFO
pelican_alias.egg-info/SOURCES.txt
pelican_alias.egg-info/dependency_links.txt
pelican_alias.egg-info/not-zip-safe
pelican_alias.egg-info/requires.txt
pelican_alias.egg-info/top_level.txt