Metadata-Version: 1.0
Name: pelican-alias
Version: 1.0
Summary: Pelican plugin for creating alias pages (useful for moving from a different URL scheme such as /<year>/<month>/<title>/ as used by Wordpress).
Home-page: http://github.com/Nitron/pelican-alias
Author: Christopher Williams
Author-email: chris@christopher-williams.net
License: MIT
Download-URL: http://github.com/Nitron/pelican-alias/tarball/1.0
Keywords: pelican blog
Platform: UNKNOWN
